{
  "$schema": "http://json-schema.org/draft-07/schema#",
  "title": "MonitoringSettings",
  "type": "object",
  "x-source": "dayzexpansion.com",
  "x-modId": "expansion-core",
  "x-filePath": "Profiles/ExpansionMod/Settings/MonitoringSettings.json",
  "properties": {
    "m_Version": {
      "description": "M_version",
      "examples": [
        "1"
      ],
      "type": "integer",
      "default": 1
    },
    "Enabled": {
      "description": "Enable or disable d",
      "examples": [
        "1"
      ],
      "type": "integer",
      "enum": [
        0,
        1
      ],
      "default": 1
    }
  }
}
